{"h4vkiZyN675fXmgCrHM/Jw==":"sultan1-122x81.jpg","98Wuthu1mAw2k2EToE/lUQ==":"hp-1.1.webp","hsFXUZYPG62EwGUa9YJnBw==":"hp-1.3-320x228.jpg","bWZICVBoPGf7n9zyIAy+gw==":"hp-1.4-320x227.jpg","IjYuWlcsc6hcxCWIh0MvMA==":"hp-1.5-320x240.png","46Z+u8qw2trpY0gmeUeJKQ==":"hp-1.6.webp","0R7+PTkGrztLn7Y6i7sTlQ==":"hp-1.webp","SIrR30RFkF6QIpjymZiEpw==":"hp-2.webp","JyF3iisG8/e8GKzaws8h0g==":"hp-3.webp","f0aAf0RJIaT44aM7GajMGA==":"hp-4.webp","xn9z9xOlBz88JY3BBxGRfw==":"hp-5.webp","Z+At1uvkCq5ooZT3pjlnJg==":"hp-6.webp","2smGSaUd59ZFP3bTmPR91Q==":"hp-1.2-259x194.jpg","MtnbWO36IqQf3RUmLEithw==":"hp%20keyboard-320x240.png","a68yk12EkPL4j4QkIK6E5g==":"hp%20keyboard-320x332.jpg","oon9qW02vqhYwGo+eTFpsA==":"hp%20headset-320x240.jpg"}